picsh/__init__.py
picsh/app.py
picsh/cluster_spec.py
picsh/command_engine.py
picsh/node.py
picsh/state_change_notifier.py
picsh/util.py
picsh/bin/__init__.py
picsh/bin/picsh.py
picsh/controllers/__init__.py
picsh/controllers/base_controller.py
picsh/controllers/cluster_selection_controller.py
picsh/controllers/cluster_shell_controller.py
picsh/controllers/node_panel_controller.py
picsh/controllers/receive_buffer_controller.py
picsh/controllers/root_controller.py
picsh/controllers/single_shell_controller.py
picsh/exceptions/__init__.py
picsh/exceptions/picsh_exception.py
picsh/models/__init__.py
picsh/models/root_model.py
picsh/views/__init__.py
picsh/views/cluster_selection_view.py
picsh/views/cluster_shell_view.py
picsh/views/node_panel_view.py
picsh/views/receive_buffer_view.py
picsh/views/single_shell_view.py
picsh/views/view_names.py
picsh/widgets/__init__.py
picsh/widgets/listbox_with_mouse_events.py
picsh/widgets/selectable_row.py
picsh-0.2.1.dist-info/LICENSE
picsh-0.2.1.dist-info/METADATA
picsh-0.2.1.dist-info/WHEEL
picsh-0.2.1.dist-info/entry_points.txt
picsh-0.2.1.dist-info/top_level.txt
picsh-0.2.1.dist-info/RECORD
