Metadata-Version: 2.1
Name: picsh
Version: 0.2.1
Summary: Parallel Interactive Cluster Shell, for rapid ad-hoc cluster ops
Author-email: Ran Dugal <opensource@clusterdyne.com>
License: AGPL3
Project-URL: Homepage, https://github.com/carlsborg/picsh
Project-URL: Issues, https://github.com/carlsborg/picsh/issues
Classifier: Programming Language :: Python :: 3
Classifier: License :: OSI Approved :: GNU Affero General Public License v3
Classifier: Operating System :: OS Independent
Classifier: Topic :: System :: Distributed Computing
Classifier: Topic :: System :: System Shells
Classifier: Topic :: System :: Systems Administration
Classifier: Topic :: System :: Clustering
Classifier: Development Status :: 4 - Beta
Classifier: Environment :: Console
Classifier: Environment :: Console :: Curses
Classifier: Operating System :: POSIX
Classifier: Intended Audience :: Developers
Classifier: Intended Audience :: System Administrators
Classifier: Intended Audience :: Information Technology
Classifier: Natural Language :: English
Requires-Python: >=3.6
License-File: LICENSE
Requires-Dist: asyncssh
Requires-Dist: urwid
Requires-Dist: pyyaml
Requires-Dist: colorama
